{"frames": [

{
	"filename": "Celular_00000.png",
	"frame": {"x":1,"y":1,"w":400,"h":400},
	"rotated": false,
	"trimmed": false,
	"spriteSourceSize": {"x":0,"y":0,"w":400,"h":400},
	"sourceSize": {"w":400,"h":400}
},
{
	"filename": "Celular_00001.png",
	"frame": {"x":403,"y":1,"w":400,"h":400},
	"rotated": false,
	"trimmed": false,
	"spriteSourceSize": {"x":0,"y":0,"w":400,"h":400},
	"sourceSize": {"w":400,"h":400}
},
{
	"filename": "Celular_00002.png",
	"frame": {"x":805,"y":1,"w":400,"h":400},
	"rotated": false,
	"trimmed": false,
	"spriteSourceSize": {"x":0,"y":0,"w":400,"h":400},
	"sourceSize": {"w":400,"h":400}
},
{
	"filename": "Celular_00003.png",
	"frame": {"x":1207,"y":1,"w":400,"h":400},
	"rotated": false,
	"trimmed": false,
	"spriteSourceSize": {"x":0,"y":0,"w":400,"h":400},
	"sourceSize": {"w":400,"h":400}
},
{
	"filename": "Celular_00004.png",
	"frame": {"x":1609,"y":1,"w":400,"h":400},
	"rotated": false,
	"trimmed": false,
	"spriteSourceSize": {"x":0,"y":0,"w":400,"h":400},
	"sourceSize": {"w":400,"h":400}
},
{
	"filename": "Celular_00005.png",
	"frame": {"x":1,"y":403,"w":400,"h":400},
	"rotated": false,
	"trimmed": false,
	"spriteSourceSize": {"x":0,"y":0,"w":400,"h":400},
	"sourceSize": {"w":400,"h":400}
},
{
	"filename": "Celular_00006.png",
	"frame": {"x":403,"y":403,"w":400,"h":400},
	"rotated": false,
	"trimmed": false,
	"spriteSourceSize": {"x":0,"y":0,"w":400,"h":400},
	"sourceSize": {"w":400,"h":400}
},
{
	"filename": "Celular_00007.png",
	"frame": {"x":805,"y":403,"w":400,"h":400},
	"rotated": false,
	"trimmed": false,
	"spriteSourceSize": {"x":0,"y":0,"w":400,"h":400},
	"sourceSize": {"w":400,"h":400}
},
{
	"filename": "Celular_00008.png",
	"frame": {"x":1207,"y":403,"w":400,"h":400},
	"rotated": false,
	"trimmed": false,
	"spriteSourceSize": {"x":0,"y":0,"w":400,"h":400},
	"sourceSize": {"w":400,"h":400}
},
{
	"filename": "Celular_00009.png",
	"frame": {"x":1609,"y":403,"w":400,"h":400},
	"rotated": false,
	"trimmed": false,
	"spriteSourceSize": {"x":0,"y":0,"w":400,"h":400},
	"sourceSize": {"w":400,"h":400}
},
{
	"filename": "Celular_00010.png",
	"frame": {"x":1,"y":805,"w":400,"h":400},
	"rotated": false,
	"trimmed": false,
	"spriteSourceSize": {"x":0,"y":0,"w":400,"h":400},
	"sourceSize": {"w":400,"h":400}
},
{
	"filename": "Celular_00011.png",
	"frame": {"x":403,"y":805,"w":400,"h":400},
	"rotated": false,
	"trimmed": false,
	"spriteSourceSize": {"x":0,"y":0,"w":400,"h":400},
	"sourceSize": {"w":400,"h":400}
},
{
	"filename": "Celular_00012.png",
	"frame": {"x":805,"y":805,"w":400,"h":400},
	"rotated": false,
	"trimmed": false,
	"spriteSourceSize": {"x":0,"y":0,"w":400,"h":400},
	"sourceSize": {"w":400,"h":400}
},
{
	"filename": "Celular_00013.png",
	"frame": {"x":1207,"y":805,"w":400,"h":400},
	"rotated": false,
	"trimmed": false,
	"spriteSourceSize": {"x":0,"y":0,"w":400,"h":400},
	"sourceSize": {"w":400,"h":400}
},
{
	"filename": "Celular_00014.png",
	"frame": {"x":1609,"y":805,"w":400,"h":400},
	"rotated": false,
	"trimmed": false,
	"spriteSourceSize": {"x":0,"y":0,"w":400,"h":400},
	"sourceSize": {"w":400,"h":400}
},
{
	"filename": "Celular_00015.png",
	"frame": {"x":1,"y":1207,"w":400,"h":400},
	"rotated": false,
	"trimmed": false,
	"spriteSourceSize": {"x":0,"y":0,"w":400,"h":400},
	"sourceSize": {"w":400,"h":400}
},
{
	"filename": "Celular_00016.png",
	"frame": {"x":403,"y":1207,"w":400,"h":400},
	"rotated": false,
	"trimmed": false,
	"spriteSourceSize": {"x":0,"y":0,"w":400,"h":400},
	"sourceSize": {"w":400,"h":400}
},
{
	"filename": "Celular_00017.png",
	"frame": {"x":805,"y":1207,"w":400,"h":400},
	"rotated": false,
	"trimmed": false,
	"spriteSourceSize": {"x":0,"y":0,"w":400,"h":400},
	"sourceSize": {"w":400,"h":400}
},
{
	"filename": "Celular_00018.png",
	"frame": {"x":1207,"y":1207,"w":400,"h":400},
	"rotated": false,
	"trimmed": false,
	"spriteSourceSize": {"x":0,"y":0,"w":400,"h":400},
	"sourceSize": {"w":400,"h":400}
},
{
	"filename": "Celular_00019.png",
	"frame": {"x":1609,"y":1207,"w":400,"h":400},
	"rotated": false,
	"trimmed": false,
	"spriteSourceSize": {"x":0,"y":0,"w":400,"h":400},
	"sourceSize": {"w":400,"h":400}
},
{
	"filename": "Celular_00020.png",
	"frame": {"x":1,"y":1609,"w":400,"h":400},
	"rotated": false,
	"trimmed": false,
	"spriteSourceSize": {"x":0,"y":0,"w":400,"h":400},
	"sourceSize": {"w":400,"h":400}
},
{
	"filename": "Celular_00021.png",
	"frame": {"x":403,"y":1609,"w":400,"h":400},
	"rotated": false,
	"trimmed": false,
	"spriteSourceSize": {"x":0,"y":0,"w":400,"h":400},
	"sourceSize": {"w":400,"h":400}
},
{
	"filename": "Celular_00022.png",
	"frame": {"x":805,"y":1609,"w":400,"h":400},
	"rotated": false,
	"trimmed": false,
	"spriteSourceSize": {"x":0,"y":0,"w":400,"h":400},
	"sourceSize": {"w":400,"h":400}
},
{
	"filename": "Celular_00023.png",
	"frame": {"x":1207,"y":1609,"w":400,"h":400},
	"rotated": false,
	"trimmed": false,
	"spriteSourceSize": {"x":0,"y":0,"w":400,"h":400},
	"sourceSize": {"w":400,"h":400}
},
{
	"filename": "Celular_00024.png",
	"frame": {"x":1609,"y":1609,"w":400,"h":400},
	"rotated": false,
	"trimmed": false,
	"spriteSourceSize": {"x":0,"y":0,"w":400,"h":400},
	"sourceSize": {"w":400,"h":400}
},
{
	"filename": "Celular_00025.png",
	"frame": {"x":1,"y":2011,"w":400,"h":400},
	"rotated": false,
	"trimmed": false,
	"spriteSourceSize": {"x":0,"y":0,"w":400,"h":400},
	"sourceSize": {"w":400,"h":400}
},
{
	"filename": "Celular_00026.png",
	"frame": {"x":403,"y":2011,"w":400,"h":400},
	"rotated": false,
	"trimmed": false,
	"spriteSourceSize": {"x":0,"y":0,"w":400,"h":400},
	"sourceSize": {"w":400,"h":400}
},
{
	"filename": "Celular_00027.png",
	"frame": {"x":805,"y":2011,"w":400,"h":400},
	"rotated": false,
	"trimmed": false,
	"spriteSourceSize": {"x":0,"y":0,"w":400,"h":400},
	"sourceSize": {"w":400,"h":400}
},
{
	"filename": "Celular_00028.png",
	"frame": {"x":1207,"y":2011,"w":400,"h":400},
	"rotated": false,
	"trimmed": false,
	"spriteSourceSize": {"x":0,"y":0,"w":400,"h":400},
	"sourceSize": {"w":400,"h":400}
},
{
	"filename": "Celular_00029.png",
	"frame": {"x":1609,"y":2011,"w":400,"h":400},
	"rotated": false,
	"trimmed": false,
	"spriteSourceSize": {"x":0,"y":0,"w":400,"h":400},
	"sourceSize": {"w":400,"h":400}
},
{
	"filename": "Celular_00030.png",
	"frame": {"x":1,"y":2413,"w":400,"h":400},
	"rotated": false,
	"trimmed": false,
	"spriteSourceSize": {"x":0,"y":0,"w":400,"h":400},
	"sourceSize": {"w":400,"h":400}
},
{
	"filename": "Celular_00031.png",
	"frame": {"x":403,"y":2413,"w":400,"h":400},
	"rotated": false,
	"trimmed": false,
	"spriteSourceSize": {"x":0,"y":0,"w":400,"h":400},
	"sourceSize": {"w":400,"h":400}
},
{
	"filename": "Celular_00032.png",
	"frame": {"x":805,"y":2413,"w":400,"h":400},
	"rotated": false,
	"trimmed": false,
	"spriteSourceSize": {"x":0,"y":0,"w":400,"h":400},
	"sourceSize": {"w":400,"h":400}
},
{
	"filename": "Celular_00033.png",
	"frame": {"x":1207,"y":2413,"w":400,"h":400},
	"rotated": false,
	"trimmed": false,
	"spriteSourceSize": {"x":0,"y":0,"w":400,"h":400},
	"sourceSize": {"w":400,"h":400}
},
{
	"filename": "Celular_00034.png",
	"frame": {"x":1609,"y":2413,"w":400,"h":400},
	"rotated": false,
	"trimmed": false,
	"spriteSourceSize": {"x":0,"y":0,"w":400,"h":400},
	"sourceSize": {"w":400,"h":400}
},
{
	"filename": "Celular_00035.png",
	"frame": {"x":1,"y":2815,"w":400,"h":400},
	"rotated": false,
	"trimmed": false,
	"spriteSourceSize": {"x":0,"y":0,"w":400,"h":400},
	"sourceSize": {"w":400,"h":400}
},
{
	"filename": "Celular_00036.png",
	"frame": {"x":403,"y":2815,"w":400,"h":400},
	"rotated": false,
	"trimmed": false,
	"spriteSourceSize": {"x":0,"y":0,"w":400,"h":400},
	"sourceSize": {"w":400,"h":400}
},
{
	"filename": "Celular_00037.png",
	"frame": {"x":403,"y":2815,"w":400,"h":400},
	"rotated": false,
	"trimmed": false,
	"spriteSourceSize": {"x":0,"y":0,"w":400,"h":400},
	"sourceSize": {"w":400,"h":400}
},
{
	"filename": "Celular_00038.png",
	"frame": {"x":805,"y":2815,"w":400,"h":400},
	"rotated": false,
	"trimmed": false,
	"spriteSourceSize": {"x":0,"y":0,"w":400,"h":400},
	"sourceSize": {"w":400,"h":400}
},
{
	"filename": "Celular_00039.png",
	"frame": {"x":1207,"y":2815,"w":400,"h":400},
	"rotated": false,
	"trimmed": false,
	"spriteSourceSize": {"x":0,"y":0,"w":400,"h":400},
	"sourceSize": {"w":400,"h":400}
}],
"meta": {
	"app": "https://www.codeandweb.com/texturepacker",
	"version": "1.0",
	"image": "sprite.png",
	"format": "RGBA8888",
	"size": {"w":2010,"h":3216},
	"scale": "1",
	"smartupdate": "$TexturePacker:SmartUpdate:860da7d8b13ac6b88ab401d3fe4fbb0e:c225a5be2e35ac19ecd18107bd2aef19:68d88b3cf7eafc9b5accfffdfb2fda91$"
}
}
